Metadata-Version: 1.2
Name: petl-fwf
Version: 0.0.2
Summary: Additional methods for the petl library that enable reading fixed-width files
Home-page: https://github.com/JoBrad/petl_fwf
Author: JoBrad
Author-email: jtbradley+petlfwf@gmail.com
License: MIT License
Keywords: petl fixed-width text
Platform: UNKNOWN
Classifier: Intended Audience :: Developers
Classifier: License :: OSI Approved :: MIT License
Classifier: Programming Language :: Python :: 2
Classifier: Programming Language :: Python :: 2.7
Classifier: Programming Language :: Python :: 3
Classifier: Programming Language :: Python :: 3.4
Classifier: Programming Language :: Python :: 3.5
Classifier: Programming Language :: Python :: 3.6
Classifier: Topic :: Software Development :: Libraries :: Python Modules
Requires-Python: >=2.7
